truthound_dashboard/__init__.py
truthound_dashboard/__main__.py
truthound_dashboard/cli.py
truthound_dashboard/config.py
truthound_dashboard/main.py
truthound_dashboard/api/__init__.py
truthound_dashboard/api/alerts.py
truthound_dashboard/api/anomaly.py
truthound_dashboard/api/catalog.py
truthound_dashboard/api/collaboration.py
truthound_dashboard/api/cross_alerts.py
truthound_dashboard/api/deps.py
truthound_dashboard/api/drift.py
truthound_dashboard/api/drift_monitor.py
truthound_dashboard/api/enterprise_sampling.py
truthound_dashboard/api/error_handlers.py
truthound_dashboard/api/glossary.py
truthound_dashboard/api/health.py
truthound_dashboard/api/history.py
truthound_dashboard/api/lineage.py
truthound_dashboard/api/maintenance.py
truthound_dashboard/api/mask.py
truthound_dashboard/api/middleware.py
truthound_dashboard/api/model_monitoring.py
truthound_dashboard/api/notifications.py
truthound_dashboard/api/notifications_advanced.py
truthound_dashboard/api/observability.py
truthound_dashboard/api/plugins.py
truthound_dashboard/api/profile.py
truthound_dashboard/api/quality_reporter.py
truthound_dashboard/api/reports.py
truthound_dashboard/api/router.py
truthound_dashboard/api/rule_suggestions.py
truthound_dashboard/api/rules.py
truthound_dashboard/api/scan.py
truthound_dashboard/api/schedules.py
truthound_dashboard/api/schema_evolution.py
truthound_dashboard/api/schema_watcher.py
truthound_dashboard/api/schemas.py
truthound_dashboard/api/sources.py
truthound_dashboard/api/tiering.py
truthound_dashboard/api/triggers.py
truthound_dashboard/api/validations.py
truthound_dashboard/api/validators.py
truthound_dashboard/api/versioning.py
truthound_dashboard/api/websocket.py
truthound_dashboard/core/__init__.py
truthound_dashboard/core/anomaly.py
truthound_dashboard/core/anomaly_explainer.py
truthound_dashboard/core/base.py
truthound_dashboard/core/cache.py
truthound_dashboard/core/cached_services.py
truthound_dashboard/core/charts.py
truthound_dashboard-1.5.0.dist-info/METADATA
truthound_dashboard-1.5.0.dist-info/WHEEL
truthound_dashboard-1.5.0.dist-info/entry_points.txt
truthound_dashboard-1.5.0.dist-info/licenses/LICENSE
truthound_dashboard-1.5.0.dist-info/RECORD
