Metadata-Version: 2.4
Name: truthound-dashboard
Version: 1.5.0
Summary: Open-source data quality dashboard - GX Cloud alternative
Author-email: Truthound Team <team@truthound.dev>
License-Expression: Apache-2.0
License-File: LICENSE
Keywords: dashboard,data-quality,monitoring,truthound,validation
Classifier: Development Status :: 3 - Alpha
Classifier: Framework :: FastAPI
Classifier: Intended Audience :: Developers
Classifier: Intended Audience :: Science/Research
Classifier: License :: OSI Approved :: Apache Software License
Classifier: Operating System :: OS Independent
Classifier: Programming Language :: Python :: 3.11
Classifier: Programming Language :: Python :: 3.12
Classifier: Topic :: Database
Classifier: Topic :: Scientific/Engineering
Requires-Python: >=3.11
Requires-Dist: aiosmtplib>=3.0.0
Requires-Dist: aiosqlite>=0.19.0
Requires-Dist: apscheduler>=3.10.0
Requires-Dist: cryptography>=41.0.0
Requires-Dist: fastapi>=0.110.0
Requires-Dist: httpx>=0.26.0
Requires-Dist: jinja2>=3.1.0
Requires-Dist: numpy>=1.24.0
Requires-Dist: pydantic-settings>=2.1.0
Requires-Dist: pydantic>=2.5.0
Requires-Dist: sqlalchemy[asyncio]>=2.0.0
Requires-Dist: truthound>=1.2.10
Requires-Dist: uvicorn[standard]>=0.27.0
Provides-Extra: dev
Requires-Dist: black>=23.0.0; extra == 'dev'
Requires-Dist: httpx>=0.26.0; extra == 'dev'
Requires-Dist: mypy>=1.8.0; extra == 'dev'
Requires-Dist: pytest-asyncio>=0.21.0; extra == 'dev'
Requires-Dist: pytest-cov>=4.1.0; extra == 'dev'
Requires-Dist: pytest>=7.4.0; extra == 'dev'
Requires-Dist: ruff>=0.1.0; extra == 'dev'
Provides-Extra: redis
Requires-Dist: redis>=5.0.0; extra == 'redis'
Provides-Extra: translate
